dps/__init__.py
dps/__main__.py
dps_liumou_Stable/__init__.py
dps_liumou_Stable/__main__.py
dps_liumou_Stable/docker_executor.py
dps_liumou_Stable/docker_pull_smart.py
dps_liumou_Stable/image_utils.py
dps_liumou_Stable/mirror_client.py
dps_liumou_Stable/version.py
dps_liumou_stable-1.1.3.dist-info/licenses/LICENSE
dps_liumou_stable-1.1.3.dist-info/METADATA
dps_liumou_stable-1.1.3.dist-info/WHEEL
dps_liumou_stable-1.1.3.dist-info/entry_points.txt
dps_liumou_stable-1.1.3.dist-info/top_level.txt
dps_liumou_stable-1.1.3.dist-info/RECORD
