Metadata-Version: 2.4
Name: dps_liumou_Stable
Version: 1.1.3
Summary: 智能Docker镜像拉取工具 - 自动选择最优镜像源
Home-page: https://gitee.com/liumou/dps_liumou_Stable
Author: 坐公交也用券
Author-email: liumou <liumou.site@qq.com>
Maintainer-email: liumou <liumou.site@qq.com>
License: MIT
Project-URL: Homepage, https://gitee.com/liumou_site/DockerPullSmart
Project-URL: Documentation, https://gitee.com/liumou_site/DockerPullSmart/blob/main/README.md
Project-URL: Repository, https://gitee.com/liumou_site/DockerPullSmart
Project-URL: Bug Tracker, https://gitee.com/liumou_site/DockerPullSmart/issues
Keywords: docker,pull,mirror,accelerate,smart,intelligent
Platform: Windows
Platform: Linux
Platform: macOS
Classifier: Development Status :: 5 - Production/Stable
Classifier: Intended Audience :: Developers
Classifier: Intended Audience :: System Administrators
Classifier: License :: OSI Approved :: MIT License
Classifier: Operating System :: OS Independent
Classifier: Programming Language :: Python :: 3
Classifier: Programming Language :: Python :: 3.6
Classifier: Programming Language :: Python :: 3.7
Classifier: Programming Language :: Python :: 3.8
Classifier: Programming Language :: Python :: 3.9
Classifier: Programming Language :: Python :: 3.10
Classifier: Programming Language :: Python :: 3.11
Classifier: Programming Language :: Python :: 3.12
Classifier: Programming Language :: Python :: 3.13
Classifier: Topic :: Software Development :: Libraries :: Python Modules
Classifier: Topic :: System :: Systems Administration
Classifier: Topic :: Utilities
Requires-Python: >=3.6
License-File: LICENSE
Requires-Dist: requests>=2.28.0
Requires-Dist: urllib3>=1.26.0
Provides-Extra: dev
Requires-Dist: pytest>=6.0; extra == "dev"
Requires-Dist: black>=21.0; extra == "dev"
Requires-Dist: flake8>=3.8; extra == "dev"
Dynamic: author
Dynamic: home-page
Dynamic: license-file
Dynamic: platform
Dynamic: requires-python
